gfz_client/__about__.py
gfz_client/__init__.py
gfz_client/__version__.py
gfz_client/abstract_client.py
gfz_client/backends.py
gfz_client/client.py
gfz_client/exceptions.py
gfz_client/settings.py
gfz_client/types.py
gfz_client/utils.py
gfz_api_client-0.1.0.dist-info/LICENSE
gfz_api_client-0.1.0.dist-info/METADATA
gfz_api_client-0.1.0.dist-info/WHEEL
gfz_api_client-0.1.0.dist-info/top_level.txt
gfz_api_client-0.1.0.dist-info/RECORD
