Metadata-Version: 2.1
Name: gfz_api_client
Version: 0.1.0
Summary: GFZ Helmholtz Centre for Geosciences Web Service API Client
Home-page: https://github.com/mmatroskin/gfz_api_client
Author: Maksim Tulin
Project-URL: Source, https://github.com/mmatroskin/gfz_api_client
Classifier: Development Status :: 4 - Beta
Classifier: Environment :: Web Environment
Classifier: Intended Audience :: Developers
Classifier: Intended Audience :: Science/Research
Classifier: License :: OSI Approved :: MIT License
Classifier: Operating System :: OS Independent
Classifier: Programming Language :: Python
Classifier: Programming Language :: Python :: 3
Classifier: Programming Language :: Python :: 3.10
Classifier: Programming Language :: Python :: 3.11
Classifier: Programming Language :: Python :: 3.12
Classifier: Programming Language :: Python :: 3.13
Classifier: Programming Language :: Python :: 3 :: Only
Requires-Python: >=3.10
License-File: LICENSE
Requires-Dist: aiohttp <4.0,>=3.8
Requires-Dist: requests <3.0.0,>=2.0.0
Requires-Dist: ujson <6.0,>=5.0
